whatlang/__init__.py
whatlang/predict_lang.py
whatlang/test_predict_lang.py
whatlang/model/lid.176.ftz
whatlang-1.0.2.dist-info/DESCRIPTION.rst
whatlang-1.0.2.dist-info/METADATA
whatlang-1.0.2.dist-info/RECORD
whatlang-1.0.2.dist-info/WHEEL
whatlang-1.0.2.dist-info/metadata.json
whatlang-1.0.2.dist-info/top_level.txt
