Metadata-Version: 2.0
Name: whatlang
Version: 1.0.2
Summary: Lightning Fast Language Prediction powered by Fasttext.
Home-page: https://github.com/whiletruelearn/whatlang
Author: Krishna Sangeeth
Author-email: kskrishnasangeeth@gmail.com
License: Licensed under the Apache License, Version 2.0 (the "License");
Requires-Dist: Cython
Requires-Dist: cysignals
Requires-Dist: pyfasttext
